segment/__init__.py
segment/analyticsqueue.py
segment/cli.py
segment/consts.py
segment/core.py
segment_queue-1.1.0.dist-info/DESCRIPTION.rst
segment_queue-1.1.0.dist-info/METADATA
segment_queue-1.1.0.dist-info/RECORD
segment_queue-1.1.0.dist-info/WHEEL
segment_queue-1.1.0.dist-info/entry_points.txt
segment_queue-1.1.0.dist-info/metadata.json
segment_queue-1.1.0.dist-info/top_level.txt
