Metadata-Version: 2.0
Name: segment-queue
Version: 1.1.0
Summary: Wrap Segment's python library to use Redis as the queue
Home-page: https://github.com/gitprime/segment-queue
Author: George Hickman
Author-email: george@ghickman.co.uk
License: MIT
Platform: any
Requires-Dist: analytics-python
Requires-Dist: click
Requires-Dist: python-dateutil
Requires-Dist: redis
